Lab4_scanner/buffer.v
module buffer(data_in, data_out, address, scanning, flush, transfer, clk, rst);
	//output
	wire [79:0] mem_out;
	input [7:0] data_in;
	output reg [7:0] data_out = 8'b0;

	output reg [3:0] address;
	input rst, clk, scanning, flush, transfer;
	reg [7:0] m [0:9];
	reg WE = 1'b0, WIPE = 1'b0;
	

	reg [1:0] state = 2'b00;
	reg [1:0] next = 2'b00;
	
	parameter
	writing = 2'b10, reading = 2'b01, hold = 2'b00, dump = 2'b11;
	
	integer i;
	genvar k;
	generate for (k=0; k < 10; k = k+1) begin: memout
		assign mem_out[8*(k+1)-1 : 8*k] = m[k];
	end endgenerate
	
	always@(*) begin
		if(WE)
			m[address] = data_in;
		else if(WIPE) begin
			for(i=0; i<10; i=i+1) 
				m[i] = 8'b0;
		end
		
		data_out = m[address];
	end
	
	always@(posedge clk or negedge rst) begin
		if(~rst) begin
			state <= dump;
		end else begin
			state <= next;
		end
	end
	

	always@(clk) begin
	
		if(~clk) begin
			WE <= 1'b0;
			WIPE <= 1'b0;
		end
		
		if(clk) begin
			if(flush) begin
				next <= dump;
			end else if (scanning) begin
				WE <= 1'b1;
				next <= writing;
				if(state!= writing)
					address <= 4'd0;
			end else if (transfer) begin
				next <= reading;
				if(state!= reading)
					address <= 4'd0;
			end else
				next <= hold;
		
		
		
			case(state)
				writing: if(address <= 4'd9 && next == writing) begin
								WE <= 1'b1;
								address <= address + 4'd1;
						end else 
								WE <= 1'b0;
				reading: if(address <= 4'd9 && next == reading) begin
								address <= address + 1'd1;
						end else if(address >= 4'd10) begin
								WIPE <= 1'b1;
						end		
				hold: begin
							address <= address;
						end
				dump: begin

						WIPE <= 1'b1;			

						address <= 4'd0;
						end
			endcase
		end
	end
	

	
	
	
endmodule

Lab4_scanner/buffer_TB.v
`include "buffer.v"
module buffer_TB();

	reg [7:0] data_in;
	reg rst, clk, scanning, flush, transfer;
	wire [7:0] data_out;
	wire [3:0] data_count;
	wire [79:0] mem_out;
	buffer dut(mem_out, data_in, data_out, data_count, scanning, flush, transfer, clk, rst);
	
	
	always #1 clk = ~clk;
	parameter delay = 2;
	integer j;
	initial begin
		data_in = 8'd0; rst = 0; clk = 1; scanning = 0; flush = 0; transfer = 0;
		#delay;
		rst = 1;
		#delay;
		scanning = 1;
		data_in = 8'd0;
		for(j=0;j<10;j=j+1) begin
			#delay;
			data_in = j+5;
		end
		#delay;
		#delay;
		#delay;
		#delay;
		#delay;
		#delay;
		#delay;
		scanning = 0;
		#delay;
		transfer = 1;
		for(j=0;j<10;j=j+1) begin
			#delay;
		end
		#delay;
		$finish;
	end
	
	initial begin
		$dumpfile("buffer.vcd");
		$dumpvars(1,dut);

	
	end
	
	
	
	
endmodule

Lab4_scanner/buffer.vcd
$date
	Wed Nov 30 15:56:17 2016
$end
$version
	Icarus Verilog
$end
$timescale
	1s
$end
$scope module buffer_TB $end
$scope module dut $end
$var wire 1 ! clk $end
$var wire 8 " data_in [7:0] $end
$var wire 1 # flush $end
$var wire 1 $ rst $end
$var wire 1 % scanning $end
$var wire 1 & transfer $end
$var wire 80 ' mem_out [79:0] $end
$var reg 1 ( WE $end
$var reg 1 ) WIPE $end
$var reg 4 * address [3:0] $end
$var reg 8 + data_out [7:0] $end
$var reg 2 , next [1:0] $end
$var reg 2 - state [1:0] $end
$var integer 32 . i [31:0] $end
$upscope $end
$upscope $end
$enddefinitions $end
#0
$dumpvars
bx .
b11 -
b0 ,
bx +
bx *
0)
0(
bx '
0&
0%
0$
0#
b0 "
1!
$end
#1
0!
#2
b0 +
b0 '
b1010 .
b0 *
1)
b0 -
1!
1$
#3
0)
0!
#4
b10 ,
1(
1!
1%
#5
0(
0!
#6
b101 +
b101 '
1(
b10 -
1!
b101 "
#7
0(
0!
#8
b110 +
b11000000101 '
b1 *
1(
1!
b110 "
#9
0(
0!
#10
b111 +
b1110000011000000101 '
b10 *
1(
1!
b111 "
#11
0(
0!
#12
b1000 +
b1000000001110000011000000101 '
b11 *
1(
1!
b1000 "
#13
0(
0!
#14
b1001 +
b100100001000000001110000011000000101 '
b100 *
1(
1!
b1001 "
#15
0(
0!
#16
b1010 +
b10100000100100001000000001110000011000000101 '
b101 *
1(
1!
b1010 "
#17
0(
0!
#18
b1011 +
b1011000010100000100100001000000001110000011000000101 '
b110 *
1(
1!
b1011 "
#19
0(
0!
#20
b1100 +
b110000001011000010100000100100001000000001110000011000000101 '
b111 *
1(
1!
b1100 "
#21
0(
0!
#22
b1101 +
b11010000110000001011000010100000100100001000000001110000011000000101 '
b1000 *
1(
1!
b1101 "
#23
0(
0!
#24
b1110 +
b1110000011010000110000001011000010100000100100001000000001110000011000000101 '
b1001 *
1(
1!
b1110 "
#25
0(
0!
#26
bx +
b1010 *
1(
1!
#27
0(
0!
#28
0(
1!
#29
0!
#30
0(
1!
#31
0!
#32
0(
1!
#33
0!
#34
0(
1!
#35
0!
#36
0(
1!
#37
0!
#38
b0 ,
1!
0%
#39
0!
#40
b101 +
b0 *
b1 ,
b0 -
1!
1&
#41
0!
#42
b1 -
1!
#43
0!
#44
b110 +
b1 *
1!
#45
0!
#46
b111 +
b10 *
1!
#47
0!
#48
b1000 +
b11 *
1!
#49
0!
#50
b1001 +
b100 *
1!
#51
0!
#52
b1010 +
b101 *
1!
#53
0!
#54
b1011 +
b110 *
1!
#55
0!
#56
b1100 +
b111 *
1!
#57
0!
#58
b1101 +
b1000 *
1!
#59
0!
#60
b1110 +
b1001 *
1!
#61
0!
#62
bx +
b1010 *
1!
#63
0!
#64
b0 '
b1010 .
1)
1!
#65
0)
0!
#66
b1010 .
1)
1!
