Lab4_scanner/buffer_new.v
module buffer_new(data_out, data_in, address, read_address, wr_en, clk, mem_rst);

	output [7:0] data_out;
	output reg [3:0] address;
	input [3:0] read_address;
	input [7:0] data_in;
	input wr_en, clk, mem_rst;
	
	reg [7:0] m [0:9];
	
	assign data_out = m[read_address];
	integer i;
	always@(wr_en or ~mem_rst) begin
		if(~mem_rst) begin
			for(i=0; i<10; i=i+1)
				m[i] <= 8'b0;
			
			address <= 4'd0;
		end else if (wr_en)
			m[address] <= data_in;
		else if (~wr_en)
			address <= address + 1'd1;
	end
	
	
endmodule

Lab4_scanner/scanner.v
//`include "buffer_new.v"

module scanner (address, data_out, start_scan, data_in, ready_second_buffer, start_second_buffer, 
				ready_to_transfer, transfer, flush_signal, go_to_standby, state, wr_en, read_inc, clk, rst);
	output reg [2:0] state;
	output wire [7:0] data_out;
	output wire [3:0] address;
	output reg ready_second_buffer = 1'b0, start_second_buffer = 1'b0, ready_to_transfer;
	
	input [7:0] data_in;
	input start_scan, transfer, go_to_standby, flush_signal, clk, rst;
	input wr_en, read_inc;
	reg [3:0] read_address = 4'b0;
	reg mem_rst, read_inc_delayed, read_inc_edge;

	reg [2:0] next;
	
	buffer_new buff (data_out, data_in, address, read_address, wr_en, clk, mem_rst);

	parameter lowPower = 3'b000, active = 3'b001, standby = 3'b010, idle = 3'b011, flush = 3'b100, transtage = 3'b101;

	always @(posedge clk or negedge rst) begin
		if (~rst) begin
			state <= lowPower;
		end else begin
			state <= next;
		end
	end

	always @(posedge clk) begin
		read_inc_delayed <= read_inc;
		read_inc_edge <= read_inc ^ read_inc_delayed;
	end

	always @(posedge clk) begin
		case (state)
			lowPower: 	begin
							ready_to_transfer <= 1'b0;
							ready_second_buffer <= 1'b0;
							start_second_buffer <= 1'b0;
							mem_rst <= 1'b0;
							read_address <= 4'b0;
							if (start_scan && transfer == 1'b0)
								next <= active;
							else if (go_to_standby) 
								next <= standby;
							else
								next <= lowPower;
							end
			active:		begin
							mem_rst <= 1'b1;
							if(transfer) begin
								next <= transtage;
							end else if (address == 4'd10) begin
								next <= idle;
							end else 
								next <= active;

							if (address >= 4'd7) begin
								ready_to_transfer <= 1'b1;
								ready_second_buffer <= 1'b1;
								
							end
							if (address >= 4'd8) 
								start_second_buffer <= 1'b1;

						end
			standby: 	begin
							mem_rst <= 1'b1;
							if (start_scan && transfer == 1'b0) 
								next <= active;
							else 
								next <= standby;
						end
			idle: 		begin
							mem_rst <= 1'b1;
							ready_second_buffer <= 1'b0;
							start_second_buffer <= 1'b0;
							ready_to_transfer <= 1'b1;
							if (transfer) begin
								next <= transtage;
							end
							else if (flush_signal)
								next <= flush;
							else begin
								next <= idle;
							end
						end
			flush: 		begin
							mem_rst <= 1'b0;
							if(address == 4'd0)
								next <= lowPower;
							else
								next <= flush;
						end
			transtage : begin
							mem_rst <= 1'b1;
							//start_second_buffer <= 1'b0;
							if(read_address > 4'd9)
								next <= lowPower;
							else if (read_inc_edge && read_inc) begin
								read_address <= read_address + 1'b1;
								next <= transtage;
							end else 
								next <= transtage;
						end
								
		endcase
	end
endmodule

Lab4_scanner/scanner_testbench.v
`include "scanner.v"
module scanner_testbench();
	wire [7:0] data_out;
	wire [2:0] state;
	wire ready_second_buffer, start_second_buffer, ready_to_transfer;
	wire [3:0] address;

	reg start_scan, transfer, go_to_standby, flush_signal, read_inc, wr_en, clk, rst;
	reg [7:0] data_in;

	always #1 clk = ~clk;
	

	scanner dut (address, data_out, start_scan, data_in, ready_second_buffer, start_second_buffer, 
				ready_to_transfer, transfer, flush_signal, go_to_standby, state, wr_en, read_inc, clk, rst);

	parameter stimdelay = 5000, delay = 10;
	integer i;
	initial begin
		rst = 1'b1;clk = 1;transfer = 1'b0;flush_signal = 0; read_inc = 0;start_scan = 1'b0;wr_en = 0;go_to_standby = 0;
		#delay;
		rst= 1'b0;
		#delay;
		rst = 1'b1;
		#delay;
		start_scan = 1'b1;
		#delay;
		start_scan = 1'b0;
		data_in = 8'd5;
		for (i = 0; i < 10; i=i+1) begin
			#delay;
			wr_en = 1'b1;
			#delay;
			wr_en = 1'b0;
			#delay;
			data_in = data_in + 1;
		end
		#delay
		transfer = 1'b1;
		#delay
		transfer = 1'b0;
		for (i = 0; i <10; i=i+1) begin
			#delay;
			read_inc = 1;
			#delay;
			read_inc = 0;
		end
			
		#stimdelay;
		$finish;
	end

	initial begin
		$dumpfile("scanner.vcd");
		$dumpvars(1, dut);
	end


endmodule

Lab4_scanner/scanner.vcd
$date
	Fri Dec 02 14:28:01 2016
$end
$version
	Icarus Verilog
$end
$timescale
	1s
$end
$scope module scanner_testbench $end
$scope module dut $end
$var wire 1 ! clk $end
$var wire 8 " data_in [7:0] $end
$var wire 1 # flush_signal $end
$var wire 1 $ go_to_standby $end
$var wire 1 % read_inc $end
$var wire 1 & rst $end
$var wire 1 ' start_scan $end
$var wire 1 ( transfer $end
$var wire 1 ) wr_en $end
$var wire 8 * data_out [7:0] $end
$var wire 4 + address [3:0] $end
$var reg 1 , mem_rst $end
$var reg 3 - next [2:0] $end
$var reg 4 . read_address [3:0] $end
$var reg 1 / read_inc_delayed $end
$var reg 1 0 read_inc_edge $end
$var reg 1 1 ready_second_buffer $end
$var reg 1 2 ready_to_transfer $end
$var reg 1 3 start_second_buffer $end
$var reg 3 4 state [2:0] $end
$upscope $end
$upscope $end
$enddefinitions $end
#0
$dumpvars
bx 4
03
x2
01
x0
0/
b0 .
bx -
x,
bx +
bx *
0)
0(
0'
1&
0%
0$
0#
bx "
1!
$end
#1
0!
#2
00
1!
#3
0!
#4
1!
#5
0!
#6
1!
#7
0!
#8
1!
#9
0!
#10
b0 4
1!
0&
#11
0!
#12
b0 +
b0 *
b0 -
0,
02
1!
#13
0!
#14
1!
#15
0!
#16
1!
#17
0!
#18
1!
#19
0!
#20
1!
1&
#21
0!
#22
1!
#23
0!
#24
1!
#25
0!
#26
1!
#27
0!
#28
1!
#29
0!
#30
b1 -
1!
1'
#31
0!
#32
b1 4
1!
#33
0!
#34
1,
1!
#35
0!
#36
1!
#37
0!
#38
1!
#39
0!
#40
1!
b101 "
0'
#41
0!
#42
1!
#43
0!
#44
1!
#45
0!
#46
1!
#47
0!
#48
1!
#49
0!
#50
b101 *
1!
1)
#51
0!
#52
1!
#53
0!
#54
1!
#55
0!
#56
1!
#57
0!
#58
1!
#59
0!
#60
b1 +
1!
0)
#61
0!
#62
1!
#63
0!
#64
1!
#65
0!
#66
1!
#67
0!
#68
1!
#69
0!
#70
1!
b110 "
#71
0!
#72
1!
#73
0!
#74
1!
#75
0!
#76
1!
#77
0!
#78
1!
#79
0!
#80
1!
1)
#81
0!
#82
1!
#83
0!
#84
1!
#85
0!
#86
1!
#87
0!
#88
1!
#89
0!
#90
b10 +
1!
0)
#91
0!
#92
1!
#93
0!
#94
1!
#95
0!
#96
1!
#97
0!
#98
1!
#99
0!
#100
1!
b111 "
#101
0!
#102
1!
#103
0!
#104
1!
#105
0!
#106
1!
#107
0!
#108
1!
#109
0!
#110
1!
1)
#111
0!
#112
1!
#113
0!
#114
1!
#115
0!
#116
1!
#117
0!
#118
1!
#119
0!
#120
b11 +
1!
0)
#121
0!
#122
1!
#123
0!
#124
1!
#125
0!
#126
1!
#127
0!
#128
1!
#129
0!
#130
1!
b1000 "
#131
0!
#132
1!
#133
0!
#134
1!
#135
0!
#136
1!
#137
0!
#138
1!
#139
0!
#140
1!
1)
#141
0!
#142
1!
#143
0!
#144
1!
#145
0!
#146
1!
#147
0!
#148
1!
#149
0!
#150
b100 +
1!
0)
#151
0!
#152
1!
#153
0!
#154
1!
#155
0!
#156
1!
#157
0!
#158
1!
#159
0!
#160
1!
b1001 "
#161
0!
#162
1!
#163
0!
#164
1!
#165
0!
#166
1!
#167
0!
#168
1!
#169
0!
#170
1!
1)
#171
0!
#172
1!
#173
0!
#174
1!
#175
0!
#176
1!
#177
0!
#178
1!
#179
0!
#180
b101 +
1!
0)
#181
0!
#182
1!
#183
0!
#184
1!
#185
0!
#186
1!
#187
0!
#188
1!
#189
0!
#190
1!
b1010 "
#191
0!
#192
1!
#193
0!
#194
1!
#195
0!
#196
1!
#197
0!
#198
1!
#199
0!
#200
1!
1)
#201
0!
#202
1!
#203
0!
#204
1!
#205
0!
#206
1!
#207
0!
#208
1!
#209
0!
#210
b110 +
1!
0)
#211
0!
#212
1!
#213
0!
#214
1!
#215
0!
#216
1!
#217
0!
#218
1!
#219
0!
#220
1!
b1011 "
#221
0!
#222
1!
#223
0!
#224
1!
#225
0!
#226
1!
#227
0!
#228
1!
#229
0!
#230
1!
1)
#231
0!
#232
1!
#233
0!
#234
1!
#235
0!
#236
1!
#237
0!
#238
1!
#239
0!
#240
b111 +
1!
0)
#241
0!
#242
11
12
1!
#243
0!
#244
1!
#245
0!
#246
1!
#247
0!
#248
1!
#249
0!
#250
1!
b1100 "
#251
0!
#252
1!
#253
0!
#254
1!
#255
0!
#256
1!
#257
0!
#258
1!
#259
0!
#260
1!
1)
#261
0!
#262
1!
#263
0!
#264
1!
#265
0!
#266
1!
#267
0!
#268
1!
#269
0!
#270
b1000 +
1!
0)
#271
0!
#272
13
1!
#273
0!
#274
1!
#275
0!
#276
1!
#277
0!
#278
1!
#279
0!
#280
1!
b1101 "
#281
0!
#282
1!
#283
0!
#284
1!
#285
0!
#286
1!
#287
0!
#288
1!
#289
0!
#290
1!
1)
#291
0!
#292
1!
#293
0!
#294
1!
#295
0!
#296
1!
#297
0!
#298
1!
#299
0!
#300
b1001 +
1!
0)
#301
0!
#302
1!
#303
0!
#304
1!
#305
0!
#306
1!
#307
0!
#308
1!
#309
0!
#310
1!
b1110 "
#311
0!
#312
1!
#313
0!
#314
1!
#315
0!
#316
1!
#317
0!
#318
1!
#319
0!
#320
1!
1)
#321
0!
#322
1!
#323
0!
#324
1!
#325
0!
#326
1!
#327
0!
#328
1!
#329
0!
#330
b1010 +
1!
0)
#331
0!
#332
b11 -
1!
#333
0!
#334
b11 4
1!
#335
0!
#336
03
01
1!
#337
0!
#338
1!
#339
0!
#340
1!
b1111 "
#341
0!
#342
1!
#343
0!
#344
1!
#345
0!
#346
1!
#347
0!
#348
1!
#349
0!
#350
b101 -
1!
1(
#351
0!
#352
b101 4
1!
#353
0!
#354
1!
#355
0!
#356
1!
#357
0!
#358
1!
#359
0!
#360
1!
0(
#361
0!
#362
1!
#363
0!
#364
1!
#365
0!
#366
1!
#367
0!
#368
1!
#369
0!
#370
10
1/
1!
1%
#371
0!
#372
00
b110 *
b1 .
1!
#373
0!
#374
1!
#375
0!
#376
1!
#377
0!
#378
1!
#379
0!
#380
10
0/
1!
0%
#381
0!
#382
00
1!
#383
0!
#384
1!
#385
0!
#386
1!
#387
0!
#388
1!
#389
0!
#390
10
1/
1!
1%
#391
0!
#392
00
b111 *
b10 .
1!
#393
0!
#394
1!
#395
0!
#396
1!
#397
0!
#398
1!
#399
0!
#400
10
0/
1!
0%
#401
0!
#402
00
1!
#403
0!
#404
1!
#405
0!
#406
1!
#407
0!
#408
1!
#409
0!
#410
10
1/
1!
1%
#411
0!
#412
00
b1000 *
b11 .
1!
#413
0!
#414
1!
#415
0!
#416
1!
#417
0!
#418
1!
#419
0!
#420
10
0/
1!
0%
#421
0!
#422
00
1!
#423
0!
#424
1!
#425
0!
#426
1!
#427
0!
#428
1!
#429
0!
#430
10
1/
1!
1%
#431
0!
#432
00
b1001 *
b100 .
1!
#433
0!
#434
1!
#435
0!
#436
1!
#437
0!
#438
1!
#439
0!
#440
10
0/
1!
0%
#441
0!
#442
00
1!
#443
0!
#444
1!
#445
0!
#446
1!
#447
0!
#448
1!
#449
0!
#450
10
1/
1!
1%
#451
0!
#452
00
b1010 *
b101 .
1!
#453
0!
#454
1!
#455
0!
#456
1!
#457
0!
#458
1!
#459
0!
#460
10
0/
1!
0%
#461
0!
#462
00
1!
#463
0!
#464
1!
#465
0!
#466
1!
#467
0!
#468
1!
#469
0!
#470
10
1/
1!
1%
#471
0!
#472
00
b1011 *
b110 .
1!
#473
0!
#474
1!
#475
0!
#476
1!
#477
0!
#478
1!
#479
0!
#480
10
0/
1!
0%
#481
0!
#482
00
1!
#483
0!
#484
1!
#485
0!
#486
1!
#487
0!
#488
1!
#489
0!
#490
10
1/
1!
1%
#491
0!
#492
00
b1100 *
b111 .
1!
#493
0!
#494
1!
#495
0!
#496
1!
#497
0!
#498
1!
#499
0!
#500
10
0/
1!
0%
#501
0!
#502
00
1!
#503
0!
#504
1!
#505
0!
#506
1!
#507
0!
#508
1!
#509
0!
#510
10
1/
1!
1%
#511
0!
#512
00
b1101 *
b1000 .
1!
#513
0!
#514
1!
#515
0!
#516
1!
#517
0!
#518
1!
#519
0!
#520
10
0/
1!
0%
#521
0!
#522
00
1!
#523
0!
#524
1!
#525
0!
#526
1!
#527
0!
#528
1!
#529
0!
#530
10
1/
1!
1%
#531
0!
#532
00
b1110 *
b1001 .
1!
#533
0!
#534
1!
#535
0!
#536
1!
#537
0!
#538
1!
#539
0!
#540
10
0/
1!
0%
#541
0!
#542
00
1!
#543
0!
#544
1!
#545
0!
#546
1!
#547
0!
#548
1!
#549
0!
#550
10
1/
1!
1%
#551
0!
#552
00
bx *
b1010 .
1!
#553
0!
#554
b0 -
1!
#555
0!
#556
b0 4
1!
#557
0!
#558
b0 +
b0 *
b0 .
0,
02
1!
#559
0!
#560
10
0/
1!
0%
#561
0!
#562
00
1!
