Lab5/parallel_buffer.v
module parallel_buffer (parallel_out, serial_in, sr_clk, rst);	
	output wire [10:0] parallel_out;
	input serial_in;
	input sr_clk, rst;

	reg [10:0] bitShift = 11'b11111111111;


	always@(posedge sr_clk or negedge rst) begin
		if (~rst) begin
			bitShift <= 11'b11111111111;
		end else begin
			bitShift <= {bitShift[9:0], serial_in};
		end

	end

	assign parallel_out = bitShift;

endmodule

Lab5/parallel_buffer_TB.v
`include "parallel_buffer.v"

module parallel_buffer_TB();
	wire [10:0] parallel_out;
	reg serial_in, sr_clk, rst;

	parallel_buffer dut (parallel_out, serial_in, sr_clk, rst);	

	parameter delay = 5;
	integer i;
	initial begin
		sr_clk = 0;
		rst = 1'b0;
		
		#delay;

		rst = 1'b1;
		#1;

		for (i = 0; i < 11; i=i+1) begin
			#1
			serial_in = i % 2;
			#1
			sr_clk = 1;
			#1
			sr_clk = 0;
		end

		#delay;#delay;#delay;#delay;
		$finish;
	end

	initial begin
		$dumpfile("parallel_buffer.vcd");
		$dumpvars(1, dut);
	end


endmodule

Lab5/parallel_buffer.vcd
$date
	Sun Dec  4 15:07:07 2016
$end
$version
	Icarus Verilog
$end
$timescale
	1s
$end
$scope module parallel_buffer_TB $end
$scope module dut $end
$var wire 11 ! parallel_out [10:0] $end
$var wire 1 " rst $end
$var wire 1 # serial_in $end
$var wire 1 $ sr_clk $end
$var reg 11 % bitShift [10:0] $end
$upscope $end
$upscope $end
$enddefinitions $end
#0
$dumpvars
b11111111111 %
0$
x#
0"
b11111111111 !
$end
#5
1"
#7
0#
#8
b11111111110 %
b11111111110 !
1$
#9
0$
#10
1#
#11
b11111111101 %
b11111111101 !
1$
#12
0$
#13
0#
#14
b11111111010 %
b11111111010 !
1$
#15
0$
#16
1#
#17
b11111110101 %
b11111110101 !
1$
#18
0$
#19
0#
#20
b11111101010 %
b11111101010 !
1$
#21
0$
#22
1#
#23
b11111010101 %
b11111010101 !
1$
#24
0$
#25
0#
#26
b11110101010 %
b11110101010 !
1$
#27
0$
#28
1#
#29
b11101010101 %
b11101010101 !
1$
#30
0$
#31
0#
#32
b11010101010 %
b11010101010 !
1$
#33
0$
#34
1#
#35
b10101010101 %
b10101010101 !
1$
#36
0$
#37
0#
#38
b1010101010 %
b1010101010 !
1$
