Lab5/serial_in_ctrl.v
module serial_in_ctrl(SR_CLK, char_received, ser_data_in, clk, rst);
	output reg SR_CLK, char_received;
	input ser_data_in, clk, rst;
	reg [20:0] tBase = 21'b0;
	reg en;
	reg [3:0] BSC,BIC;
	
	always@(posedge clk) begin
		if(~rst)
			tBase <= 21'b0;
		else
			tBase <= tBase + 1'b1;
	end
	
	always@(posedge clk or negedge rst or posedge char_received) begin
		if(~rst)
			en <= 1'b0;
		else if (char_received)
			en <= 1'b0;
		else if (~ser_data_in)
			en <= 1'b1;
	end
	
	always@(posedge tBase[7]) begin // set tBase[7] for 9600(12207) baudrate
		if(~en || ~rst) begin
			BSC <= 4'b0;
		end else if (en) begin
			BSC <= BSC + 1'b1;
		end
	end
	
	always@(posedge clk) begin
		if(~rst)
			SR_CLK <= 1'b0;
		else if (BSC == 4'b0111)
			SR_CLK <= 1'b1;
		else
			SR_CLK <= 1'b0;
	end
	
	always@(posedge tBase[7]) begin
		if(~en || ~rst)begin
			BIC <= 4'd0;
			char_received <= 1'b0;
		end else if (BSC == 4'b1111 && BIC < 4'd11)
			BIC <= BIC + 4'd1;
		else if (BIC >= 4'd11) begin
			BIC <= BIC;
			char_received <= 1'b1;
		end
	end
endmodule

Lab5/parallel_buffer.v
module parallel_buffer (parallel_out, ser_data_in, sr_clk, rst);	
	output wire [10:0] parallel_out;
	input ser_data_in;
	input sr_clk, rst;

	reg [10:0] bitShift = 11'b11111111111;


	always@(posedge sr_clk or negedge rst) begin
		if (~rst) begin
			bitShift <= 11'b11111111111;
		end else begin
			bitShift <= {ser_data_in, bitShift[10:1]};
		end
	end

	assign parallel_out = bitShift;

endmodule

Lab5/serial_in.v
//`include "parallel_buffer.v"
//`include "serial_in_ctrl.v"
module serial_in(data_out, char_received, ser_data_in, clk, rst);
	output [7:0] data_out;
	output char_received;
	input ser_data_in, clk, rst;
	wire sr_clk;
	wire [10:0] parallel_out;
	assign data_out = parallel_out[8:1];
	
	
	
	parallel_buffer SR(parallel_out, ser_data_in, sr_clk, rst);
	serial_in_ctrl SR_ctrl(sr_clk, char_received, ser_data_in, clk, rst);
endmodule

Lab5/serial_inTB.v
`include "serial_in.v"
module serial_inTB();
	reg ser_data_in, clk, rst;
	wire [7:0] data_out;
	wire char_received;
	
	reg [10:0] data = 11'b11010111010;
	serial_in dut (data_out, char_received, ser_data_in, clk, rst);
	
	always #1 clk=~clk;
	parameter delay = 10, bitdelay = 64;
	integer i;
	initial begin
		rst = 0;
		clk = 1;
		ser_data_in = 1'b1;
		#delay;
		rst = 1;
		#delay;
		for(i = 0; i < 11; i=i+1) begin
			ser_data_in = data[i];
			#bitdelay;
		end
		#500;
		
		$finish;		
	
	end
	
	initial begin
		$dumpfile("serial_in.vcd");
		$dumpvars(1, dut);
	end
endmodule

Lab5/serial_in.vcd
$date
	Sun Dec 04 16:18:54 2016
$end
$version
	Icarus Verilog
$end
$timescale
	1s
$end
$scope module serial_inTB $end
$scope module dut $end
$var wire 1 ! clk $end
$var wire 1 " rst $end
$var wire 1 # ser_data_in $end
$var wire 1 $ sr_clk $end
$var wire 11 % parallel_out [10:0] $end
$var wire 8 & data_out [7:0] $end
$var wire 1 ' char_received $end
$upscope $end
$upscope $end
$enddefinitions $end
#0
$dumpvars
x'
b11111111 &
b11111111111 %
0$
1#
0"
1!
$end
#1
0!
#2
1!
#3
0!
#4
1!
#5
0!
#6
1!
#7
0!
#8
1!
#9
0!
#10
0'
1!
1"
#11
0!
#12
1!
#13
0!
#14
1!
#15
0!
#16
1!
#17
0!
#18
1!
#19
0!
#20
1!
0#
#21
0!
#22
1!
#23
0!
#24
1!
#25
0!
#26
1!
#27
0!
#28
1!
#29
0!
#30
1!
#31
0!
#32
1!
#33
0!
#34
1!
#35
0!
#36
1!
#37
0!
#38
1!
#39
0!
#40
1!
#41
0!
#42
1!
#43
0!
#44
1!
#45
0!
#46
1!
#47
0!
#48
b1111111111 %
1$
1!
#49
0!
#50
1!
#51
0!
#52
0$
1!
#53
0!
#54
1!
#55
0!
#56
1!
#57
0!
#58
1!
#59
0!
#60
1!
#61
0!
#62
1!
#63
0!
#64
1!
#65
0!
#66
1!
#67
0!
#68
1!
#69
0!
#70
1!
#71
0!
#72
1!
#73
0!
#74
1!
#75
0!
#76
1!
#77
0!
#78
1!
#79
0!
#80
1!
#81
0!
#82
1!
#83
0!
#84
1!
1#
#85
0!
#86
1!
#87
0!
#88
1!
#89
0!
#90
1!
#91
0!
#92
1!
#93
0!
#94
1!
#95
0!
#96
1!
#97
0!
#98
1!
#99
0!
#100
1!
#101
0!
#102
1!
#103
0!
#104
1!
#105
0!
#106
1!
#107
0!
#108
1!
#109
0!
#110
1!
#111
0!
#112
b10111111111 %
1$
1!
#113
0!
#114
1!
#115
0!
#116
0$
1!
#117
0!
#118
1!
#119
0!
#120
1!
#121
0!
#122
1!
#123
0!
#124
1!
#125
0!
#126
1!
#127
0!
#128
1!
#129
0!
#130
1!
#131
0!
#132
1!
#133
0!
#134
1!
#135
0!
#136
1!
#137
0!
#138
1!
#139
0!
#140
1!
#141
0!
#142
1!
#143
0!
#144
1!
#145
0!
#146
1!
#147
0!
#148
1!
0#
#149
0!
#150
1!
#151
0!
#152
1!
#153
0!
#154
1!
#155
0!
#156
1!
#157
0!
#158
1!
#159
0!
#160
1!
#161
0!
#162
1!
#163
0!
#164
1!
#165
0!
#166
1!
#167
0!
#168
1!
#169
0!
#170
1!
#171
0!
#172
1!
#173
0!
#174
1!
#175
0!
#176
b1111111 &
b1011111111 %
1$
1!
#177
0!
#178
1!
#179
0!
#180
0$
1!
#181
0!
#182
1!
#183
0!
#184
1!
#185
0!
#186
1!
#187
0!
#188
1!
#189
0!
#190
1!
#191
0!
#192
1!
#193
0!
#194
1!
#195
0!
#196
1!
#197
0!
#198
1!
#199
0!
#200
1!
#201
0!
#202
1!
#203
0!
#204
1!
#205
0!
#206
1!
#207
0!
#208
1!
#209
0!
#210
1!
#211
0!
#212
1!
1#
#213
0!
#214
1!
#215
0!
#216
1!
#217
0!
#218
1!
#219
0!
#220
1!
#221
0!
#222
1!
#223
0!
#224
1!
#225
0!
#226
1!
#227
0!
#228
1!
#229
0!
#230
1!
#231
0!
#232
1!
#233
0!
#234
1!
#235
0!
#236
1!
#237
0!
#238
1!
#239
0!
#240
b10111111 &
b10101111111 %
1$
1!
