Lab5/serial_buffer.v
module serial_buffer (bit_out, parallel_in, load, sr_clk, rst);	
	output reg bit_out;
	input [10:0] parallel_in;
	input load, sr_clk, rst;

	reg [10:0] bitShift = 11'b11111111111;


	always@(posedge sr_clk or posedge load or negedge rst) begin
		if (~rst)
			bitShift <= 11'b11111111111;
		else if (load)
			bitShift <= parallel_in;
		else if (sr_clk)
			bitShift <= {1'b1, bitShift[10:1]};

	end

	always@(posedge sr_clk) begin
		bit_out <= bitShift[0];
	end

endmodule

Lab5/serial_buffer_TB.v
`include "serial_buffer.v"

module serial_buffer_TB();
	wire bit_out;
	reg [10:0] parallel_in;
	reg load, sr_clk, rst;

	serial_buffer dut (bit_out, parallel_in, load, sr_clk, rst);	

	//always #1 sr_clk = ~sr_clk;

	parameter delay = 5;
	integer i;
	initial begin
		parallel_in = 11'b0;
		sr_clk = 0;
		load = 1'b0;
		rst = 1'b0;
		#delay;

		rst = 1'b1;
		load = 1'b1;
		parallel_in = 11'b11111010100;
		#1;
		load = 1'b0;

		for (i = 0; i < 15; i=i+1) begin
			#1
			sr_clk = 1;
			#1
			sr_clk = 0;
		end

		#delay;#delay;#delay;#delay;
		$finish;
	end

	initial begin
		$dumpfile("serial_buffer.vcd");
		$dumpvars(1, dut);
	end


endmodule

Lab5/serial_buffer.vcd
$date
	Sun Dec  4 14:10:41 2016
$end
$version
	Icarus Verilog
$end
$timescale
	1s
$end
$scope module serial_buffer_TB $end
$scope module dut $end
$var wire 1 ! load $end
$var wire 11 " parallel_in [10:0] $end
$var wire 1 # rst $end
$var wire 1 $ sr_clk $end
$var reg 11 % bitShift [10:0] $end
$var reg 1 & bit_out $end
$upscope $end
$upscope $end
$enddefinitions $end
#0
$dumpvars
x&
b11111111111 %
0$
0#
b0 "
0!
$end
#5
b11111010100 %
b11111010100 "
1!
1#
#6
0!
#7
0&
b11111101010 %
1$
#8
0$
#9
b11111110101 %
1$
#10
0$
#11
1&
b11111111010 %
1$
#12
0$
#13
0&
b11111111101 %
1$
#14
0$
#15
1&
b11111111110 %
1$
#16
0$
#17
0&
b11111111111 %
1$
#18
0$
#19
1&
1$
