Lab5/serial_out_ctrl.v
module serial_out_ctrl(SR_CLK, char_sent, trans_en, clk, rst);
	output reg SR_CLK, char_sent;
	input trans_en, clk, rst;
	
	reg [20:0] tBase = 21'b0;
	reg [3:0] BSC = 4'b0, BIC = 4'b0;
	
	always@(posedge clk) begin
		if(~rst)
			tBase <= 21'b0;
		else
			tBase <= tBase + 1'b1;
	end
	
	always@(posedge tBase[7]) begin // set tBase[7] for 9600(12207) baudrate
		if(~trans_en || ~rst) begin
			BSC <= 4'b0;
		end else if (trans_en) begin
			BSC <= BSC + 1'b1;
		end
	end
	
	always@(posedge clk) begin
		if(~rst)
			SR_CLK <= 1'b0;
		else if (BSC == 4'b1111)
			SR_CLK <= 1'b1;
		else
			SR_CLK <= 1'b0;
	end
	
	always@(posedge tBase[7]) begin
		if(~trans_en || ~rst)begin
			BIC <= 4'd0;
			char_sent <= 1'b0;
		end else if (BSC == 4'b1111 && BIC < 4'd11)
			BIC <= BIC + 4'd1;
		else if (BIC >= 4'd11) begin
			BIC <= BIC;
			char_sent <= 1'b1;
		end
	end
	
endmodule

Lab5/serial_buffer.v
module serial_buffer (bit_out, parallel_in, load, sr_clk, rst);	
	output reg bit_out;
	input [10:0] parallel_in;
	input load, sr_clk, rst;

	reg [10:0] bitShift = 11'b11111111111;


	always@(posedge sr_clk or posedge load or negedge rst) begin
		if (~rst)
			bitShift <= 11'b11111111111;
		else if (load)
			bitShift <= parallel_in;
		else if (sr_clk)
			bitShift <= {1'b1, bitShift[10:1]};

	end

	always@(posedge sr_clk or negedge rst) begin
		if (~rst)
			bit_out <= 1'b1;
		else
			bit_out <= bitShift[0];
	end

endmodule

Lab5/serial_out.v
//`include "serial_out_ctrl.v"
//`include "serial_buffer.v"

module serial_out(bit_out, char_sent, trans_en, load, data_in, clk, rst);
	output wire bit_out, char_sent;
	input trans_en, load, clk, rst;
	input [7:0] data_in;

	wire [10:0] data_in_full;

	wire parity, SR_CLK;

	assign parity =  	(data_in[0] ^ data_in[1]) ^  
                        (data_in[2] ^ data_in[3]) ^ 
                        (data_in[4] ^ data_in[5]) ^  
                        (data_in[6] ^ data_in[7]);

	assign data_in_full = {1'b1, parity, data_in, 1'b0};

	serial_buffer parallel_to_serial (bit_out, data_in_full, load, SR_CLK, rst);
	serial_out_ctrl serial_ctrl (SR_CLK, char_sent, trans_en, clk, rst);

endmodule

Lab5/serial_out_TB.v
`include "serial_out.v"

module serial_out_TB();

	wire bit_out, char_sent;
	reg trans_en, load, clk, rst;
	reg [7:0] data_in;

	serial_out dut (bit_out, char_sent, trans_en, load, data_in, clk, rst);

	always #1 clk = ~clk;

	parameter delay = 5, bitdelay = 64; 
	

	initial begin
		$dumpfile("serial_out.vcd");
		$dumpvars(1, dut);
	end

	initial begin
		clk = 1;
		rst = 0;
		load = 0;
		trans_en = 0;
		#delay;
		rst = 1;
		#delay;

		data_in = 8'b11001010;
		#delay;
		load = 1;
		#1;
		load = 0;
		#delay;
        
		trans_en = 1;
		#5000;

		$finish;
	end


endmodule

Lab5/serial_out.vcd
$date
	Sun Dec 04 16:14:59 2016
$end
$version
	Icarus Verilog
$end
$timescale
	1s
$end
$scope module serial_out_TB $end
$scope module dut $end
$var wire 1 ! clk $end
$var wire 8 " data_in [7:0] $end
$var wire 1 # load $end
$var wire 1 $ parity $end
$var wire 1 % rst $end
$var wire 1 & trans_en $end
$var wire 11 ' data_in_full [10:0] $end
$var wire 1 ( char_sent $end
$var wire 1 ) bit_out $end
$var wire 1 * SR_CLK $end
$upscope $end
$upscope $end
$enddefinitions $end
#0
$dumpvars
0*
1)
x(
b1xxxxxxxxx0 '
0&
0%
x$
0#
bx "
1!
$end
#1
0!
#2
1!
#3
0!
#4
1!
#5
0!
1%
#6
0(
1!
#7
0!
#8
1!
#9
0!
#10
0$
1!
b10110010100 '
b11001010 "
#11
0!
#12
1!
#13
0!
#14
1!
#15
0!
1#
#16
1!
0#
#17
0!
#18
1!
#19
0!
#20
1!
#21
0!
1&
#22
1!
#23
0!
#24
1!
#25
0!
#26
1!
#27
0!
#28
1!
#29
0!
#30
1!
#31
0!
#32
1!
#33
0!
#34
1!
#35
0!
#36
1!
#37
0!
#38
1!
#39
0!
#40
1!
#41
0!
#42
1!
#43
0!
#44
1!
#45
0!
#46
1!
#47
0!
#48
1!
#49
0!
#50
1!
#51
0!
#52
1!
#53
0!
#54
1!
#55
0!
#56
1!
#57
0!
#58
1!
#59
0!
#60
1!
#61
0!
#62
1!
#63
0!
#64
1!
#65
0!
#66
1!
#67
0!
#68
1!
#69
0!
#70
1!
#71
0!
#72
1!
#73
0!
#74
1!
#75
0!
#76
1!
#77
0!
#78
1!
#79
0!
#80
0)
1*
1!
