lab3/buffer.v
module buffer(data_count, scanning, flush, transfer, clk ,rst);

	output reg [6:0] data_count = 7'd0;
	input rst, clk, scanning, flush, transfer;
	reg [24:0] tBase = 25'b0;
	reg [1:0] semaphore = 2'b00;
	
	parameter
	increase = 2'b10, decrease = 2'b01, hold = 2'b00, dump = 2'b11;
	
	always@(posedge clk)
		tBase <= tBase + 1'b1;
	
	always@(posedge tBase[20]) begin
		case(semaphore)
			hold: data_count <= data_count;
			increase: if(data_count < 7'd100)
						data_count <= data_count + 1'b1;
			decrease: if(data_count > 7'd0)
						data_count <= data_count - 1'b1;
			dump: data_count <= 7'd0;
			default: data_count <= data_count;
		endcase
	end
	
	always@(posedge clk or negedge rst) begin
		if(~rst)
			semaphore <= dump;
		else if (flush)
			semaphore <= dump;
		else if (scanning)
			semaphore <= increase;
		else if (transfer)
			semaphore <= decrease;
	end
endmodule

lab3/scanner.v
`include "buffer.v"

module scanner (start_scan, data_count, ready_second_buffer, start_second_buffer, ready_to_transfer, transfer, flush_signal, go_to_standby, state, clk, rst);
	output reg [2:0] state;
	output wire [7:0] data_count;
	output reg ready_second_buffer, start_second_buffer, ready_to_transfer;
	input start_scan, transfer, go_to_standby, flush_signal, clk, rst;

	reg [2:0] next;
	reg flush_buffer;

	buffer buff (data_count, start_scan, flush_buffer, transfer, clk, rst);

	parameter lowPower = 3'b000, active = 3'b001, standby = 3'b010, idle = 3'b011, flush = 3'b100;

	always @(posedge clk or negedge rst) begin
		if (~rst) begin
			state <= lowPower;
		end else begin
			state <= next;
		end
	end

	always @(posedge clk) begin
		
		ready_second_buffer <= 1'b0;
		ready_to_transfer <= 1'b0;
		start_second_buffer <= 1'b0;
		flush_buffer <= 1'b0;
		
		case (state)
			lowPower: 	begin if (start_scan) next <= active;
							else if (go_to_standby) next <= standby;
							else next <= lowPower;
						end
			active:		begin
							if (data_count >= 8'd80) begin
								ready_to_transfer <= 1'b1;
								ready_second_buffer <= 1'b1;
							end
							if (data_count >= 8'd90) start_second_buffer <= 1'b1;
							if (transfer && data_count >= 8'd100) next <= lowPower;
							else if (~transfer && data_count >= 8'd100) next <= idle;
							else next <= active;
						end
			standby: 	begin if (start_scan) next <= active;
							else next <= standby;
						end
			idle: 		begin 
							ready_to_transfer <= 1'b1;
							if (transfer) next <= lowPower;
							else if (flush_signal) next <= flush;
							else next <= idle;
						end
			flush: 		begin
							flush_buffer <= 1'b1;
							next <= lowPower;
						end
		endcase
	end
endmodule

lab3/scanner_testbench.v
`include "scanner.v"
module scanner_testbench();
	wire [7:0] data_count;
	wire [2:0] state;
	wire ready_second_buffer, start_second_buffer, ready_to_transfer;

	reg start_scan, transfer, go_to_standby, flush_signal, clk, rst;

	always #1 clk = ~clk;
	
	scanner dut (start_scan, data_count, ready_second_buffer, start_second_buffer, ready_to_transfer, transfer, flush_signal, go_to_standby, state, clk, rst);

	parameter stimdelay = 5000;
	
	initial begin
		rst = 1'b0;clk = 1;
		#1;
		rst = 1'b1;
		#1;
		start_scan = 1'b0;
		#1;
		start_scan = 1'b1;
		transfer = 1'b0;
		#4;
		start_scan = 1'b1;
		#10;
		transfer = 1'b1;
		#stimdelay;
		$finish;
	end

	initial begin
		$dumpfile("scanner.vcd");
		$dumpvars(1, dut);
	end


endmodule

lab3/scanner.vcd
$date
	Wed Nov 16 13:01:06 2016
$end
$version
	Icarus Verilog
$end
$timescale
	1s
$end
$scope module scanner_testbench $end
$scope module dut $end
$var wire 1 ! clk $end
$var wire 8 " data_count [7:0] $end
$var wire 1 # flush_signal $end
$var wire 1 $ go_to_standby $end
$var wire 1 % rst $end
$var wire 1 & start_scan $end
$var wire 1 ' transfer $end
$var reg 1 ( flush_buffer $end
$var reg 3 ) next [2:0] $end
$var reg 1 * ready_second_buffer $end
$var reg 1 + ready_to_transfer $end
$var reg 1 , start_second_buffer $end
$var reg 3 - state [2:0] $end
$upscope $end
$upscope $end
$enddefinitions $end
#0
$dumpvars
b0 -
0,
x+
0*
bx )
0(
x'
x&
0%
x$
x#
b0 "
1!
$end
#1
1%
0!
#2
bx -
b0 )
0+
0&
1!
#3
0'
1&
0!
#4
b0 -
1!
#5
0!
#6
b1 )
1!
#7
0!
#8
b1 -
1!
#9
0!
#10
b1 "
1!
#11
0!
#12
1!
#13
0!
#14
1!
#15
0!
#16
1!
#17
0!
1'
#18
b10 "
1!
#19
0!
#20
1!
#21
0!
#22
1!
#23
0!
#24
1!
#25
0!
#26
b11 "
1!
#27
0!
#28
1!
#29
0!
#30
1!
#31
0!
#32
1!
#33
0!
#34
b100 "
1!
#35
0!
#36
1!
#37
0!
#38
1!
#39
0!
#40
1!
#41
0!
#42
b101 "
1!
#43
0!
#44
1!
#45
0!
#46
1!
#47
0!
#48
1!
#49
0!
#50
b110 "
1!
#51
0!
#52
1!
#53
0!
#54
1!
#55
0!
#56
1!
#57
0!
#58
b111 "
1!
#59
0!
#60
1!
#61
0!
#62
1!
#63
0!
#64
1!
#65
0!
#66
b1000 "
1!
#67
0!
#68
1!
#69
0!
#70
1!
#71
0!
#72
1!
#73
0!
#74
b1001 "
1!
#75
0!
#76
1!
#77
0!
#78
1!
#79
0!
#80
1!
#81
0!
#82
b1010 "
1!
#83
0!
#84
1!
#85
0!
#86
1!
#87
0!
#88
1!
#89
0!
#90
b1011 "
1!
#91
0!
#92
1!
#93
0!
#94
1!
#95
0!
#96
1!
#97
0!
#98
b1100 "
1!
#99
0!
#100
1!
#101
0!
#102
1!
#103
0!
#104
1!
#105
0!
#106
b1101 "
1!
#107
0!
#108
1!
#109
0!
#110
1!
#111
0!
#112
1!
#113
0!
#114
b1110 "
1!
#115
0!
#116
1!
#117
0!
#118
1!
#119
0!
#120
1!
#121
0!
#122
b1111 "
1!
#123
0!
#124
1!
#125
0!
#126
1!
#127
0!
#128
1!
#129
0!
#130
b10000 "
1!
#131
0!
#132
1!
#133
0!
#134
1!
#135
0!
#136
1!
#137
0!
#138
b10001 "
1!
#139
0!
#140
1!
#141
0!
#142
1!
#143
0!
#144
1!
#145
0!
#146
b10010 "
1!
#147
0!
#148
1!
#149
0!
#150
1!
#151
0!
#152
1!
#153
0!
#154
b10011 "
1!
#155
0!
#156
1!
#157
0!
#158
1!
#159
0!
#160
1!
#161
0!
#162
b10100 "
1!
#163
0!
#164
1!
#165
0!
#166
1!
#167
0!
#168
1!
#169
0!
#170
b10101 "
1!
#171
0!
#172
1!
#173
0!
#174
1!
#175
0!
#176
1!
#177
0!
#178
b10110 "
1!
#179
0!
#180
1!
#181
0!
#182
1!
#183
0!
#184
1!
#185
0!
#186
b10111 "
1!
#187
0!
#188
1!
#189
0!
#190
1!
#191
0!
#192
1!
#193
0!
#194
b11000 "
1!
#195
0!
#196
1!
#197
0!
#198
1!
#199
0!
#200
1!
#201
0!
#202
b11001 "
1!
#203
0!
#204
1!
#205
0!
#206
1!
#207
0!
#208
1!
#209
0!
#210
b11010 "
1!
#211
0!
#212
1!
#213
0!
#214
1!
#215
0!
#216
1!
#217
0!
#218
b11011 "
1!
#219
0!
#220
1!
#221
0!
#222
1!
#223
0!
#224
1!
#225
0!
#226
b11100 "
1!
#227
0!
#228
1!
#229
0!
#230
1!
#231
0!
#232
1!
#233
0!
#234
b11101 "
1!
#235
0!
#236
1!
#237
0!
#238
1!
#239
0!
#240
1!
#241
0!
#242
b11110 "
1!
#243
0!
#244
1!
#245
0!
#246
1!
#247
0!
#248
1!
#249
0!
#250
b11111 "
1!
#251
0!
#252
1!
#253
0!
#254
1!
#255
0!
#256
1!
#257
0!
#258
b100000 "
1!
#259
0!
#260
1!
#261
0!
#262
1!
#263
0!
#264
1!
#265
0!
#266
b100001 "
1!
#267
0!
#268
1!
#269
0!
#270
1!
#271
0!
#272
1!
#273
0!
#274
b100010 "
1!
#275
0!
#276
1!
#277
0!
#278
1!
#279
0!
#280
1!
#281
0!
#282
b100011 "
1!
#283
0!
#284
1!
#285
0!
#286
1!
#287
0!
#288
1!
#289
0!
#290
b100100 "
1!
#291
0!
#292
1!
#293
0!
#294
1!
#295
0!
#296
1!
#297
0!
#298
b100101 "
1!
#299
0!
#300
1!
#301
0!
#302
1!
#303
0!
#304
1!
#305
0!
#306
b100110 "
1!
#307
0!
#308
1!
#309
0!
#310
1!
#311
0!
#312
1!
#313
0!
#314
b100111 "
1!
#315
0!
#316
1!
#317
0!
#318
1!
#319
0!
#320
1!
#321
0!
#322
b101000 "
1!
#323
0!
#324
1!
#325
0!
#326
1!
#327
0!
#328
1!
#329
0!
#330
b101001 "
1!
#331
0!
#332
1!
#333
0!
#334
1!
#335
0!
#336
1!
#337
0!
#338
b101010 "
1!
#339
0!
#340
1!
#341
0!
#342
1!
#343
0!
#344
1!
#345
0!
#346
b101011 "
1!
#347
0!
#348
1!
#349
0!
#350
1!
#351
0!
#352
1!
#353
0!
#354
b101100 "
1!
#355
0!
#356
1!
#357
0!
#358
1!
#359
0!
#360
1!
#361
0!
#362
b101101 "
1!
#363
0!
#364
1!
#365
0!
#366
1!
#367
0!
#368
1!
#369
0!
#370
b101110 "
1!
#371
0!
#372
1!
#373
0!
#374
1!
#375
0!
#376
1!
#377
0!
#378
b101111 "
1!
#379
0!
#380
1!
#381
0!
#382
1!
#383
0!
#384
1!
#385
0!
#386
b110000 "
1!
#387
0!
#388
1!
#389
0!
#390
1!
#391
0!
#392
1!
#393
0!
#394
b110001 "
1!
#395
0!
#396
1!
#397
0!
#398
1!
#399
0!
#400
1!
#401
0!
#402
b110010 "
1!
#403
0!
#404
1!
#405
0!
#406
1!
#407
0!
#408
1!
#409
0!
#410
b110011 "
1!
#411
0!
#412
1!
#413
0!
#414
1!
#415
0!
#416
1!
#417
0!
#418
b110100 "
1!
#419
0!
#420
1!
#421
0!
#422
1!
#423
0!
#424
1!
#425
0!
#426
b110101 "
1!
#427
0!
#428
1!
#429
0!
#430
1!
#431
0!
#432
1!
#433
0!
#434
b110110 "
1!
#435
0!
#436
1!
#437
0!
#438
1!
#439
0!
#440
1!
#441
0!
#442
b110111 "
1!
#443
0!
#444
1!
#445
0!
#446
1!
#447
0!
#448
1!
#449
0!
#450
b111000 "
1!
#451
0!
#452
1!
#453
0!
#454
1!
#455
0!
#456
1!
#457
0!
#458
b111001 "
1!
#459
0!
#460
1!
#461
0!
#462
1!
#463
0!
#464
1!
#465
0!
#466
b111010 "
1!
#467
0!
#468
1!
#469
0!
#470
1!
#471
0!
#472
1!
#473
0!
#474
b111011 "
1!
#475
0!
#476
1!
#477
0!
#478
1!
#479
0!
#480
1!
#481
0!
#482
b111100 "
1!
#483
0!
#484
1!
#485
0!
#486
1!
#487
0!
#488
1!
#489
0!
#490
b111101 "
1!
#491
0!
#492
1!
#493
0!
#494
1!
#495
0!
#496
1!
#497
0!
#498
b111110 "
1!
#499
0!
#500
1!
#501
0!
#502
1!
#503
0!
#504
1!
#505
0!
#506
b111111 "
1!
#507
0!
#508
1!
#509
0!
#510
1!
#511
0!
#512
1!
#513
0!
#514
b1000000 "
1!
#515
0!
#516
1!
#517
0!
#518
1!
#519
0!
#520
1!
#521
0!
#522
b1000001 "
1!
#523
0!
#524
1!
#525
0!
#526
1!
#527
0!
#528
1!
#529
0!
#530
b1000010 "
1!
#531
0!
#532
1!
#533
0!
#534
1!
#535
0!
#536
1!
#537
0!
#538
b1000011 "
1!
#539
0!
#540
1!
#541
0!
#542
1!
#543
0!
#544
1!
#545
0!
#546
b1000100 "
1!
#547
0!
#548
1!
#549
0!
#550
1!
#551
0!
#552
1!
#553
0!
#554
b1000101 "
1!
#555
0!
#556
1!
#557
0!
#558
1!
#559
0!
#560
1!
#561
0!
#562
b1000110 "
1!
#563
0!
#564
1!
#565
0!
#566
1!
#567
0!
#568
1!
#569
0!
#570
b1000111 "
1!
#571
0!
#572
1!
#573
0!
#574
1!
#575
0!
#576
1!
#577
0!
#578
b1001000 "
1!
#579
0!
#580
1!
#581
0!
#582
1!
#583
0!
#584
1!
#585
0!
#586
b1001001 "
1!
#587
0!
#588
1!
#589
0!
#590
1!
#591
0!
#592
1!
#593
0!
#594
b1001010 "
1!
#595
0!
#596
1!
#597
0!
#598
1!
#599
0!
#600
1!
#601
0!
#602
b1001011 "
1!
#603
0!
#604
1!
#605
0!
#606
1!
#607
0!
#608
1!
#609
0!
#610
b1001100 "
1!
#611
0!
#612
1!
#613
0!
#614
1!
#615
0!
#616
1!
#617
0!
#618
b1001101 "
1!
#619
0!
#620
1!
#621
0!
#622
1!
#623
0!
#624
1!
#625
0!
#626
b1001110 "
1!
#627
0!
#628
1!
#629
0!
#630
1!
#631
0!
#632
1!
#633
0!
#634
b1001111 "
1!
#635
0!
#636
1!
#637
0!
#638
1!
#639
0!
#640
1!
#641
0!
#642
b1010000 "
1!
#643
0!
#644
1*
1+
1!
#645
0!
#646
1!
#647
0!
#648
1!
#649
0!
#650
b1010001 "
1!
#651
0!
#652
1!
#653
0!
#654
1!
#655
0!
#656
1!
#657
0!
#658
b1010010 "
1!
#659
0!
#660
1!
#661
0!
#662
1!
#663
0!
#664
1!
#665
0!
#666
b1010011 "
1!
#667
0!
#668
1!
#669
0!
#670
1!
#671
0!
#672
1!
#673
0!
#674
b1010100 "
1!
#675
0!
#676
1!
#677
0!
#678
1!
#679
0!
#680
1!
#681
0!
#682
b1010101 "
1!
#683
0!
#684
1!
#685
0!
#686
1!
#687
0!
#688
1!
#689
0!
#690
b1010110 "
1!
#691
0!
#692
1!
#693
0!
#694
1!
#695
0!
#696
1!
#697
0!
#698
b1010111 "
1!
#699
0!
#700
1!
#701
0!
#702
1!
#703
0!
#704
1!
#705
0!
#706
b1011000 "
1!
#707
0!
#708
1!
#709
0!
#710
1!
#711
0!
#712
1!
#713
0!
#714
b1011001 "
1!
#715
0!
#716
1!
#717
0!
#718
1!
#719
0!
#720
1!
#721
0!
#722
b1011010 "
1!
#723
0!
#724
1,
1!
#725
0!
#726
1!
#727
0!
#728
1!
#729
0!
#730
b1011011 "
1!
#731
0!
#732
1!
#733
0!
#734
1!
#735
0!
#736
1!
#737
0!
#738
b1011100 "
1!
#739
0!
#740
1!
#741
0!
#742
1!
#743
0!
#744
1!
#745
0!
#746
b1011101 "
1!
#747
0!
#748
1!
#749
0!
#750
1!
#751
0!
#752
1!
#753
0!
#754
b1011110 "
1!
#755
0!
#756
1!
#757
0!
#758
1!
#759
0!
#760
1!
#761
0!
#762
b1011111 "
1!
#763
0!
#764
1!
#765
0!
#766
1!
#767
0!
#768
1!
#769
0!
#770
b1100000 "
1!
#771
0!
#772
1!
#773
0!
#774
1!
#775
0!
#776
1!
#777
0!
#778
b1100001 "
1!
#779
0!
#780
1!
#781
0!
#782
1!
#783
0!
#784
1!
#785
0!
#786
b1100010 "
1!
#787
0!
#788
1!
#789
0!
#790
1!
#791
0!
#792
1!
#793
0!
#794
b1100011 "
1!
#795
0!
#796
1!
#797
0!
#798
1!
#799
0!
#800
1!
#801
0!
#802
b1100100 "
1!
#803
0!
#804
b11 )
1!
#805
0!
#806
b11 -
1!
#807
0!
#808
b0 )
0,
0*
1!
#809
0!
#810
b0 -
1!
#811
0!
#812
0+
1!
